{"date":"2024-05-23T09:12:14.887Z","courseId":"17","assignment":"AP-Spring03-CA6","trace":{"content":"#include \"date.hpp\"\n\nDate::Date()\n{\n    day = 1;\n    month = 1;\n    year = 1;\n}\n\n\nDate::Date(int d , int m , int y)\n{\n    day = d;\n    month = m;\n    year = y;\n}\n\nvoid Date::Print()\n{\n    std::ostringstream S;\n    std::cout << year << DATE_SEPRATOR << month << DATE_SEPRATOR << day;\n} \n\nbool Date::is_Equal_Date(Date *date)\n{\n    if(date->day == day && date->month == month && date->year == year)\n        return true;\n    return false;\n}\n\n\nstd::string Date::get_Date()\n{\n    std::ostringstream S;\n    S << year << DATE_SEPRATOR << month << DATE_SEPRATOR << day;\n    return S.str();\n}","filename":"/home/erfan/Desktop/Project6/A6_1/date.cpp","identifier":"Save Document","languageId":"cpp","version":129,"lineCount":37},"failed":false}