{"date":"2024-06-05T14:10:50.243Z","courseId":"17","assignment":"AP-Spring03-CA6-phase2","trace":{"content":"#ifndef IOHANDLER\n#define IOHANDLER\n\n#include <iostream>\n#include <vector>\n\nclass IOHandler\n{\npublic:\n    IOHandler();\n    ~IOHandler();\n    void Print_Data(std::vector <std::string> data_vector);\n    void Print_Data(std::string data_string);\n    void Print_Error(std::string error_text);\n    bool get_Command_Line(std::string &cmd_line);\n    \n};\n\n\n#endif","filename":"/home/erfan/Desktop/Project6_2/A6_1/io_Handler.hpp","identifier":"Save Document","languageId":"cpp","version":27,"lineCount":20},"failed":false}