{"date":"2024-06-05T13:53:05.241Z","courseId":"17","assignment":"AP-Spring03-CA6-phase2","trace":{"content":"#ifndef UT_POST\n#define UT_POST\n\n#include <string>\n#include <vector>\n#include <sstream>\n#include \"messages.hpp\"\n\n\nclass UT_Media\n{\npublic:\n\n\tUT_Media(std::string i,std::string t,std::string m,std::string a);\n\tvirtual ~UT_Media();\n\tvirtual std::string get_All_Info() = 0;\n\tstd::string get_Info();\n\tstd::string get_Id();\n\tvoid set_Id(std::string i);\n\tbool is_Valid_Id(std::string target_id);\n\tbool Compare_Id(UT_Media *target_post);\n\t\nprotected:\n\tstd::string id;\n\tstd::string title;\n\tstd::string message;\n\tstd::string author;\n\t\n};\n\nclass UT_Post : public UT_Media\n{\npublic:\n\tUT_Post(std::string i,std::string t,std::string m,std::string a,std::string im_p);\n\tstd::string get_Info_Include_Author();\n\tstd::string get_All_Info_Include_Author();\n\tstd::string get_All_Info();\n\nprivate:\n\tstd::string image_path;\n\n};\n\nclass TA_Form : public UT_Media\n{\npublic:\n\tTA_Form(std::string i,std::string t,std::string m,std::string a,std::string c_i,std::string c_info);\n\tvoid Add_TA_Request(std::string student_id);\n\tstd::string get_All_Info();\n\tstd::string get_Course_Id();\n\tstd::vector<std::string> get_Volunteers();\n\nprivate:\n\tstd::string course_id;\n\tstd::string course_information;\n\tstd::vector<std::string> volunteers_id;\n};\n\n#endif","filename":"/home/erfan/Desktop/Project6_2/A6_1/UT_media.hpp","identifier":"Save Document","languageId":"cpp","version":33,"lineCount":59},"failed":false}